verilog/uartRx.v
module uartRx #(
    parameter integer OVERSAMPLE = 16
) (
    input  wire        clk,
    input  wire        rst_n,
    input  wire        tick,         // oversample tick
    input  wire        i_rx,         // серійний вхід (idle=1)
    output reg [7:0]   o_data,       // прийнятий байт (MSB-first)
    output reg         o_data_ready, // імпульс коли байт готовий
    output reg         o_frame_err   // фреймінг помилка (стоп-біт не 1)
);

    // --- Оголошення станів ---
    parameter [1:0]
        RX_IDLE  = 2'b00,
        RX_START = 2'b01,
        RX_DATA  = 2'b10,
        RX_STOP  = 2'b11;

    reg [1:0] state;           // поточний стан
    reg [4:0] oversample_cnt;  // лічильник тиків (ширший для MSB-first)
    reg [2:0] bit_index;       // індекс біта (0..7)
    reg [7:0] shift_reg;       // прийняті біти
    reg       rx_sync;         // синхронізований вхід
    reg       rx_sync_0;       // проміжний регістр для синхронізації

    // --- Синхронізація входу ---
    always @(posedge clk or negedge rst_n) begin
        if (!rst_n) begin
            rx_sync_0 <= 1'b1;
            rx_sync   <= 1'b1;
        end else begin
            rx_sync_0 <= i_rx;
            rx_sync   <= rx_sync_0;
        end
    end

    // --- Головна станова машина ---
    always @(posedge clk or negedge rst_n) begin
        if (!rst_n) begin
            state          <= RX_IDLE;
            oversample_cnt <= 0;
            bit_index      <= 0;
            shift_reg      <= 8'h00;
            o_data         <= 8'h00;
            o_data_ready   <= 1'b0;
            o_frame_err    <= 1'b0;
        end else begin
            o_data_ready <= 1'b0; // короткий імпульс при готовності

            case (state)
                RX_IDLE: begin
                    o_frame_err <= 1'b0;
                    if (!rx_sync) begin
                        oversample_cnt <= 0;
                        state <= RX_START;
                    end
                end

                RX_START: begin
                    if (tick) begin
                        if (oversample_cnt == (OVERSAMPLE/2 - 1)) begin
                            oversample_cnt <= 0;
                            if (!rx_sync) begin
                                bit_index <= 0;
                                state <= RX_DATA;
                            end else begin
                                state <= RX_IDLE; // false start
                            end
                        end else begin
                            oversample_cnt <= oversample_cnt + 1;
                        end
                    end
                end

                RX_DATA: begin
                    if (tick) begin
                        if (oversample_cnt == (OVERSAMPLE - 1)) begin
                            oversample_cnt <= 0;
                            // MSB-first: новий біт у старший біт
                            shift_reg <= {shift_reg[6:0], rx_sync};
                            bit_index <= bit_index + 1;
                            if (bit_index == 7) state <= RX_STOP;
                        end else begin
                            oversample_cnt <= oversample_cnt + 1;
                        end
                    end
                end

                RX_STOP: begin
                    if (tick) begin
                        if (oversample_cnt == (OVERSAMPLE - 1)) begin
                            oversample_cnt <= 0;
                            o_data <= shift_reg;
                            o_data_ready <= 1'b1;
                            o_frame_err <= ~rx_sync; // стоп-біт повинен бути 1
                            state <= RX_IDLE;
                        end else begin
                            oversample_cnt <= oversample_cnt + 1;
                        end
                    end
                end

                default: state <= RX_IDLE;
            endcase
        end
    end

endmodule

verilog/uartTx.v
// uartTx.v
// Простий UART передавач (8N1) з використанням oversample tick.
// Порти:
//  i_data  - 8-бітний байт для відправки
//  i_send  - 1-пульс/1-логічний запуск передачі (рекомендується тримати 1 такт)
//  o_tx    - серійний лінійний вихід (idle = 1)
//  o_busy  - високий поки йде передача байта
//  o_done  - короткий імпульс у циклі коли байт відправлено

module uartTx #(
    parameter integer OVERSAMPLE = 16
) (
    input  wire        clk,
    input  wire        rst_n,
    input  wire        tick,       // oversample tick (1 такт на oversample частоту)
    input  wire [7:0]  i_data,
    input  wire        i_send,     // подати 1 для початку передачі (пульс або рівень)
    output reg         o_tx,
    output reg         o_busy,
    output reg         o_done
);

    // --- Станова машина відправки ---
    // Замість typedef enum logic [1:0] використовуємо параметри
    parameter [1:0]
        TX_IDLE  = 2'b00,
        TX_START = 2'b01,
        TX_DATA  = 2'b10,
        TX_STOP  = 2'b11;

    reg [1:0] state;          // поточний стан
    reg [3:0] oversample_cnt; // рахує OVERSAMPLE циклів для одного біту
    reg [2:0] bit_index;      // індекс бітів (0..7)
    reg [7:0] shift_reg;      // регістр для зсуву бітів

    // --- Основний процес ---
    always @(posedge clk or negedge rst_n) begin
        if (!rst_n) begin
            state          <= TX_IDLE;
            o_tx           <= 1'b1;
            o_busy         <= 1'b0;
            o_done         <= 1'b0;
            oversample_cnt <= 4'd0;
            bit_index      <= 3'd0;
            shift_reg      <= 8'h00;
        end else begin
            o_done <= 1'b0; // скидаємо done сигнал, буде встановлено при завершенні передачі

            case (state)
                TX_IDLE: begin
                    o_tx   <= 1'b1;
                    o_busy <= 1'b0;
                    if (i_send) begin
                        // зберігаємо дані і переходимо на старт-біт
                        shift_reg      <= i_data;
                        oversample_cnt <= 4'd0;
                        bit_index      <= 3'd0;
                        o_busy         <= 1'b1;
                        state          <= TX_START;
                    end
                end

                TX_START: begin
                    // відправляємо старт-біт (0) протягом OVERSAMPLE тиків
                    o_tx <= 1'b0;
                    if (tick) begin
                        if (oversample_cnt == (OVERSAMPLE - 1)) begin
                            oversample_cnt <= 4'd0;
                            state <= TX_DATA;
                        end else begin
                            oversample_cnt <= oversample_cnt + 1'b1;
                        end
                    end
                end

                TX_DATA: begin
                    // відправка 8 бітів (LSB першим)
                    o_tx <= shift_reg[0];
                    if (tick) begin
                        if (oversample_cnt == (OVERSAMPLE - 1)) begin
                            oversample_cnt <= 4'd0;
                            shift_reg <= {1'b0, shift_reg[7:1]}; // зсув вправо
                            if (bit_index == 3'd7) begin
                                bit_index <= 3'd0;
                                state <= TX_STOP;
                            end else begin
                                bit_index <= bit_index + 1'b1;
                            end
                        end else begin
                            oversample_cnt <= oversample_cnt + 1'b1;
                        end
                    end
                end

                TX_STOP: begin
                    // відправляємо стоп-біт(и) = 1. Тут 1 стоп-біт.
                    o_tx <= 1'b1;
                    if (tick) begin
                        if (oversample_cnt == (OVERSAMPLE - 1)) begin
                            oversample_cnt <= 4'd0;
                            state <= TX_IDLE;
                            o_busy <= 1'b0;
                            o_done <= 1'b1; // повідомляємо що байт відправлено
                        end else begin
                            oversample_cnt <= oversample_cnt + 1'b1;
                        end
                    end
                end

                default: state <= TX_IDLE;
            endcase
        end
    end

endmodule

verilog/baud.v
// baud.v
// Генератор імпульсів для UART з оверсемплінгом.
// Параметри:
//  CLOCK_FREQ  - частота системного годинника (Hz)
//  BAUD        - бажана швидкість UART (бод)
//  OVERSAMPLE  - множник оверсемплінгу (наприклад 16)
// Вихід tick видає імпульс з частотою BAUD * OVERSAMPLE.

module baud #(
    parameter integer CLOCK_FREQ = 50000000, // 50 MHz
    parameter integer BAUD       = 115200,
    parameter integer OVERSAMPLE = 16
) (
    input  wire clk,      // системний годинник
    input  wire rst_n,    // активний низький скидання
    output reg  tick      // одноцикловий імпульс на кожен oversample tick
);

    // Обчислення кількості тактів системного годинника на 1 oversample-tick.
    // Якщо значення неціле, використовується ціла частина (integer division).
    localparam integer CLKS_PER_TICK = CLOCK_FREQ / (BAUD * OVERSAMPLE);

    // Розрядність лічильника
    localparam integer CNT_WIDTH = $clog2(CLKS_PER_TICK > 0 ? CLKS_PER_TICK : 1);

    reg [CNT_WIDTH-1:0] counter;

    always @(posedge clk or negedge rst_n) begin
        if (!rst_n) begin
            counter <= 0;
            tick    <= 1'b0;
        end else begin
            if (counter == CLKS_PER_TICK-1) begin
                counter <= 0;
                tick    <= 1'b1; // генеруємо одноцикловий імпульс
            end else begin
                counter <= counter + 1;
                tick    <= 1'b0;
            end
        end
    end

endmodule

verilog/techbanch.v
`timescale 1us/1ns
// -------------------------------------------------------------
// techbanch.v
// Testbench для UART Tx/Rx з автоматичним завершенням і VCD
// -------------------------------------------------------------
module techbanch;

    localparam integer CLOCK_FREQ = 1_000_000; // 1 MHz
    localparam integer BAUD       = 9600;
    localparam integer OVERSAMPLE = 16;

    reg clk;
    reg rst_n;

    wire tx_line;
    reg  rx_line;

    reg  [7:0] tx_data;
    reg        tx_send;
    wire       tx_busy;
    wire       tx_done;

    wire [7:0] rx_data;
    wire       rx_ready;
    wire       rx_frame_err;

    wire tick;

    // ---------------------------------------------------------
    // Генерація тактового сигналу
    // ---------------------------------------------------------
    initial begin
        clk = 0;
        forever #0.5 clk = ~clk; // 1 MHz
    end

    // ---------------------------------------------------------
    // Генерація скидання і VCD
    // ---------------------------------------------------------
    initial begin
        $dumpfile("techbanch.vcd");
        $dumpvars(0, techbanch);
        rst_n = 0;
        #5;
        rst_n = 1;
    end

    // ---------------------------------------------------------
    // Інстанціація модулів
    // ---------------------------------------------------------
    baud #(
        .CLOCK_FREQ(CLOCK_FREQ),
        .BAUD(BAUD),
        .OVERSAMPLE(OVERSAMPLE)
    ) u_baud (
        .clk(clk),
        .rst_n(rst_n),
        .tick(tick)
    );

    uartTx #(
        .OVERSAMPLE(OVERSAMPLE)
    ) u_tx (
        .clk(clk),
        .rst_n(rst_n),
        .tick(tick),
        .i_data(tx_data),
        .i_send(tx_send),
        .o_tx(tx_line),
        .o_busy(tx_busy),
        .o_done(tx_done)
    );

    uartRx #(
        .OVERSAMPLE(OVERSAMPLE)
    ) u_rx (
        .clk(clk),
        .rst_n(rst_n),
        .tick(tick),
        .i_rx(rx_line),
        .o_data(rx_data),
        .o_data_ready(rx_ready),
        .o_frame_err(rx_frame_err)
    );

    // ---------------------------------------------------------
    // Моніторинг RX
    // ---------------------------------------------------------
    always @(posedge rx_ready) begin
        $display("[%0t us] >>> RX received byte: %h (frame_err=%b)",
                 $time, rx_data, rx_frame_err);
    end

    // ---------------------------------------------------------
    // Основний тест
    // ---------------------------------------------------------
    initial begin
        // Початкові значення
        tx_data = 8'h00;
        tx_send = 1'b0;
        rx_line = 1'b1; // idle

        // Очікуємо скидання
        wait(rst_n == 1);
        #10;

        // --- Test 1: TX ---
        $display("\n=== Test 1: TX transmission ===");
        send_byte(8'h55);
        send_byte(8'hA5);
        send_byte(8'hFF);
        send_byte(8'h00);
        $display("=== Test 1 completed ===\n");

        // --- Test 2: RX ---
        $display("=== Test 2: RX reception simulation ===");
        send_uart_byte_to_rx(8'hC1);
        send_uart_byte_to_rx(8'h7F);
        $display("=== Test 2 completed ===\n");

        #100;
        $display("=== All tests finished ===");
        $finish;
    end

    // ---------------------------------------------------------
    // Завдання: відправка байта у Tx
    // ---------------------------------------------------------
    task send_byte(input [7:0] data);
        begin
            @(posedge clk);
            tx_data <= data;
            tx_send <= 1'b1;
            @(posedge clk);
            tx_send <= 1'b0;
            wait(tx_done);
            $display("[%0t us] TX completed transmission of byte: %h", $time, data);
        end
    endtask

    // ---------------------------------------------------------
    // Завдання: імітація UART-передачі у Rx
    // ---------------------------------------------------------
task send_uart_byte_to_rx(input [7:0] data);
    integer i, j;
    begin
        // --- Старт-біт (0) ---
        rx_line = 1'b0;
        for (j = 0; j < OVERSAMPLE; j = j + 1)
            @(posedge tick);

        // --- Біти даних (MSB першим) ---
        for (i = 7; i >= 0; i = i - 1) begin
            rx_line = data[i];
            for (j = 0; j < OVERSAMPLE; j = j + 1)
                @(posedge tick);
        end

        // --- Стоп-біт (1) ---
        rx_line = 1'b1;
        for (j = 0; j < OVERSAMPLE; j = j + 1)
            @(posedge tick);

        // --- Пауза між байтами ---
        for (j = 0; j < OVERSAMPLE * 2; j = j + 1)
            @(posedge tick);
    end
endtask

endmodule

verilog/techbanch.vcd
$date
	Wed Nov 12 01:18:05 2025
$end
$version
	Icarus Verilog
$end
$timescale
	1ns
$end
$scope module techbanch $end
$var wire 1 ! tx_line $end
$var wire 1 " tx_done $end
$var wire 1 # tx_busy $end
$var wire 1 $ tick $end
$var wire 1 % rx_ready $end
$var wire 1 & rx_frame_err $end
$var wire 8 ' rx_data [7:0] $end
$var parameter 32 ( BAUD $end
$var parameter 32 ) CLOCK_FREQ $end
$var parameter 32 * OVERSAMPLE $end
$var reg 1 + clk $end
$var reg 1 , rst_n $end
$var reg 1 - rx_line $end
$var reg 8 . tx_data [7:0] $end
$var reg 1 / tx_send $end
$scope module u_baud $end
$var wire 1 + clk $end
$var wire 1 , rst_n $end
$var parameter 32 0 BAUD $end
$var parameter 32 1 CLKS_PER_TICK $end
$var parameter 32 2 CLOCK_FREQ $end
$var parameter 32 3 CNT_WIDTH $end
$var parameter 32 4 OVERSAMPLE $end
$var reg 3 5 counter [2:0] $end
$var reg 1 $ tick $end
$upscope $end
$scope module u_rx $end
$var wire 1 + clk $end
$var wire 1 - i_rx $end
$var wire 1 , rst_n $end
$var wire 1 $ tick $end
$var parameter 32 6 OVERSAMPLE $end
$var parameter 2 7 RX_DATA $end
$var parameter 2 8 RX_IDLE $end
$var parameter 2 9 RX_START $end
$var parameter 2 : RX_STOP $end
$var reg 3 ; bit_index [2:0] $end
$var reg 8 < o_data [7:0] $end
$var reg 1 % o_data_ready $end
$var reg 1 & o_frame_err $end
$var reg 5 = oversample_cnt [4:0] $end
$var reg 1 > rx_sync $end
$var reg 1 ? rx_sync_0 $end
$var reg 8 @ shift_reg [7:0] $end
$var reg 2 A state [1:0] $end
$upscope $end
$scope module u_tx $end
$var wire 1 + clk $end
$var wire 8 B i_data [7:0] $end
$var wire 1 / i_send $end
$var wire 1 , rst_n $end
$var wire 1 $ tick $end
$var parameter 32 C OVERSAMPLE $end
$var parameter 2 D TX_DATA $end
$var parameter 2 E TX_IDLE $end
$var parameter 2 F TX_START $end
$var parameter 2 G TX_STOP $end
$var reg 3 H bit_index [2:0] $end
$var reg 1 # o_busy $end
$var reg 1 " o_done $end
$var reg 1 ! o_tx $end
$var reg 4 I oversample_cnt [3:0] $end
$var reg 8 J shift_reg [7:0] $end
$var reg 2 K state [1:0] $end
$upscope $end
$scope task send_byte $end
$var reg 8 L data [7:0] $end
$upscope $end
$scope task send_uart_byte_to_rx $end
$var reg 8 M data [7:0] $end
$var integer 32 N i [31:0] $end
$var integer 32 O j [31:0] $end
$upscope $end
$upscope $end
$enddefinitions $end
$comment Show the parameter values. $end
$dumpall
b11 G
b1 F
b0 E
b10 D
b10000 C
b11 :
b1 9
b0 8
b10 7
b10000 6
b10000 4
b11 3
b11110100001001000000 2
b110 1
b10010110000000 0
b10000 *
b11110100001001000000 )
b10010110000000 (
$end
#0
$dumpvars
bx O
bx N
bx M
bx L
b0 K
b0 J
b0 I
b0 H
b0 B
b0 A
b0 @
1?
1>
b0 =
b0 <
b0 ;
b0 5
0/
b0 .
1-
0,
0+
b0 '
0&
0%
0$
0#
0"
1!
$end
#500
1+
#1000
0+
#1500
1+
#2000
0+
#2500
1+
#3000
0+
#3500
1+
#4000
0+
#4500
1+
#5000
0+
1,
#5500
b1 5
1+
#6000
0+
#6500
b10 5
1+
#7000
0+
#7500
b11 5
1+
#8000
0+
#8500
b100 5
1+
#9000
0+
#9500
b101 5
1+
#10000
0+
#10500
1$
b0 5
1+
#11000
0+
#11500
0$
b1 5
1+
#12000
0+
#12500
b10 5
1+
#13000
0+
#13500
b11 5
1+
#14000
0+
#14500
b100 5
1+
#15000
0+
b1010101 L
#15500
b101 5
1/
b1010101 .
b1010101 B
1+
#16000
0+
#16500
b1 K
1#
b1010101 J
1$
b0 5
0/
1+
#17000
0+
#17500
0$
b1 5
b1 I
0!
1+
#18000
0+
#18500
b10 5
1+
#19000
0+
#19500
b11 5
1+
#20000
0+
#20500
b100 5
1+
#21000
0+
#21500
b101 5
1+
#22000
0+
#22500
1$
b0 5
1+
#23000
0+
#23500
0$
b1 5
b10 I
1+
#24000
0+
#24500
b10 5
1+
#25000
0+
#25500
b11 5
1+
#26000
0+
#26500
b100 5
1+
#27000
0+
#27500
b101 5
1+
#28000
0+
#28500
1$
b0 5
1+
#29000
0+
#29500
0$
b1 5
b11 I
1+
#30000
0+
#30500
b10 5
1+
#31000
0+
#31500
b11 5
1+
#32000
0+
#32500
b100 5
1+
#33000
0+
#33500
b101 5
1+
#34000
0+
#34500
1$
b0 5
1+
#35000
0+
#35500
0$
b1 5
b100 I
1+
#36000
0+
#36500
b10 5
1+
#37000
0+
#37500
b11 5
1+
#38000
0+
#38500
b100 5
1+
#39000
0+
#39500
b101 5
1+
#40000
0+
#40500
1$
b0 5
1+
#41000
0+
#41500
0$
b1 5
b101 I
1+
#42000
0+
#42500
b10 5
1+
#43000
0+
#43500
b11 5
1+
#44000
0+
#44500
b100 5
1+
#45000
0+
#45500
b101 5
1+
#46000
0+
#46500
1$
b0 5
1+
#47000
0+
#47500
0$
b1 5
b110 I
1+
#48000
0+
#48500
b10 5
1+
#49000
0+
#49500
b11 5
1+
#50000
0+
#50500
b100 5
1+
#51000
0+
#51500
b101 5
1+
#52000
0+
#52500
1$
b0 5
1+
#53000
0+
#53500
0$
b1 5
b111 I
1+
#54000
0+
#54500
b10 5
1+
#55000
0+
#55500
b11 5
1+
#56000
0+
#56500
b100 5
1+
#57000
0+
#57500
b101 5
1+
#58000
0+
#58500
1$
b0 5
1+
#59000
0+
#59500
0$
b1 5
b1000 I
1+
#60000
0+
#60500
b10 5
1+
#61000
0+
#61500
b11 5
1+
#62000
0+
#62500
b100 5
1+
#63000
0+
#63500
b101 5
1+
#64000
0+
#64500
1$
b0 5
1+
#65000
0+
#65500
0$
b1 5
b1001 I
1+
#66000
0+
#66500
b10 5
1+
#67000
0+
#67500
b11 5
1+
#68000
0+
#68500
b100 5
1+
#69000
0+
#69500
b101 5
1+
#70000
0+
#70500
1$
b0 5
1+
#71000
0+
#71500
0$
b1 5
b1010 I
1+
#72000
0+
#72500
b10 5
1+
#73000
0+
#73500
b11 5
1+
#74000
0+
#74500
b100 5
1+
#75000
0+
#75500
b101 5
1+
#76000
0+
#76500
1$
b0 5
1+
#77000
0+
#77500
0$
b1 5
b1011 I
1+
#78000
0+
#78500
b10 5
1+
#79000
0+
#79500
b11 5
1+
#80000
0+
#80500
b100 5
1+
#81000
0+
#81500
b101 5
1+
#82000
0+
#82500
1$
b0 5
1+
#83000
0+
#83500
0$
b1 5
b1100 I
1+
#84000
0+
#84500
b10 5
1+
#85000
0+
#85500
b11 5
1+
#86000
0+
#86500
b100 5
1+
#87000
0+
#87500
b101 5
1+
#88000
0+
#88500
1$
b0 5
1+
#89000
0+
#89500
0$
b1 5
b1101 I
1+
#90000
0+
#90500
b10 5
1+
#91000
0+
#91500
b11 5
1+
#92000
0+
#92500
b100 5
1+
#93000
0+
#93500
b101 5
1+
#94000
0+
#94500
1$
b0 5
1+
#95000
0+
#95500
0$
b1 5
b1110 I
1+
#96000
0+
#96500
b10 5
1+
#97000
0+
#97500
b11 5
1+
#98000
0+
#98500
b100 5
1+
#99000
0+
#99500
b101 5
1+
#100000
0+
#100500
1$
b0 5
1+
#101000
0+
#101500
0$
b1 5
b1111 I
1+
#102000
0+
#102500
b10 5
1+
#103000
0+
#103500
b11 5
1+
#104000
0+
#104500
b100 5
1+
#105000
0+
#105500
b101 5
1+
#106000
0+
#106500
1$
b0 5
1+
#107000
0+
#107500
0$
b1 5
b10 K
b0 I
1+
#108000
0+
#108500
1!
b10 5
1+
#109000
0+
#109500
b11 5
1+
#110000
0+
#110500
b100 5
1+
#111000
0+
#111500
b101 5
1+
#112000
0+
#112500
1$
b0 5
1+
#113000
0+
#113500
0$
b1 5
b1 I
1+
#114000
0+
#114500
b10 5
1+
#115000
0+
#115500
b11 5
1+
#116000
0+
#116500
b100 5
1+
#117000
0+
#117500
b101 5
1+
#118000
0+
#118500
1$
b0 5
1+
#119000
0+
#119500
0$
b1 5
b10 I
1+
#120000
0+
#120500
b10 5
1+
#121000
0+
#121500
b11 5
1+
#122000
0+
#122500
b100 5
1+
#123000
0+
#123500
b101 5
1+
#124000
0+
#124500
1$
b0 5
1+
#125000
0+
#125500
0$
b1 5
b11 I
1+
#126000
0+
#126500
b10 5
1+
#127000
0+
#127500
b11 5
1+
#128000
0+
#128500
b100 5
1+
#129000
0+
#129500
b101 5
1+
#130000
0+
#130500
1$
b0 5
1+
#131000
0+
#131500
0$
b1 5
b100 I
1+
#132000
0+
#132500
b10 5
1+
#133000
0+
#133500
b11 5
1+
#134000
0+
#134500
b100 5
1+
#135000
0+
#135500
b101 5
1+
#136000
0+
#136500
1$
b0 5
1+
#137000
0+
#137500
0$
b1 5
b101 I
1+
#138000
0+
#138500
b10 5
1+
#139000
0+
#139500
b11 5
1+
#140000
0+
#140500
b100 5
1+
#141000
0+
#141500
b101 5
1+
#142000
0+
#142500
1$
b0 5
1+
#143000
0+
#143500
0$
b1 5
b110 I
1+
#144000
0+
#144500
b10 5
1+
#145000
0+
#145500
b11 5
1+
#146000
0+
#146500
b100 5
1+
#147000
0+
#147500
b101 5
1+
#148000
0+
#148500
1$
b0 5
1+
#149000
0+
#149500
0$
b1 5
b111 I
1+
#150000
0+
#150500
b10 5
1+
#151000
0+
#151500
b11 5
1+
#152000
0+
#152500
b100 5
1+
#153000
0+
#153500
b101 5
1+
#154000
0+
#154500
1$
b0 5
1+
#155000
0+
#155500
0$
b1 5
b1000 I
1+
#156000
0+
#156500
b10 5
1+
#157000
0+
#157500
b11 5
1+
#158000
0+
#158500
b100 5
1+
#159000
0+
#159500
b101 5
1+
#160000
0+
#160500
1$
b0 5
1+
#161000
0+
#161500
0$
b1 5
b1001 I
1+
#162000
0+
#162500
b10 5
1+
#163000
0+
#163500
b11 5
1+
#164000
0+
#164500
b100 5
1+
#165000
0+
#165500
b101 5
1+
#166000
0+
#166500
1$
b0 5
1+
#167000
0+
#167500
0$
b1 5
b1010 I
1+
#168000
0+
#168500
b10 5
1+
#169000
0+
#169500
b11 5
1+
#170000
0+
#170500
b100 5
1+
#171000
0+
#171500
b101 5
1+
#172000
0+
#172500
1$
b0 5
1+
#173000
0+
#173500
0$
b1 5
b1011 I
1+
#174000
0+
#174500
b10 5
1+
#175000
0+
#175500
b11 5
1+
#176000
0+
#176500
b100 5
1+
#177000
0+
#177500
b101 5
1+
#178000
0+
#178500
1$
b0 5
1+
#179000
0+
#179500
0$
b1 5
b1100 I
1+
#180000
0+
#180500
b10 5
1+
#181000
0+
#181500
b11 5
1+
#182000
0+
#182500
b100 5
1+
#183000
0+
#183500
b101 5
1+
#184000
0+
#184500
1$
b0 5
1+
#185000
0+
#185500
0$
b1 5
b1101 I
1+
#186000
0+
#186500
b10 5
1+
#187000
0+
#187500
b11 5
1+
#188000
0+
#188500
b100 5
1+
#189000
0+
#189500
b101 5
1+
#190000
0+
#190500
1$
b0 5
1+
#191000
0+
#191500
0$
b1 5
b1110 I
1+
#192000
0+
#192500
b10 5
1+
#193000
0+
#193500
b11 5
1+
#194000
0+
#194500
b100 5
1+
#195000
0+
#195500
b101 5
1+
#196000
0+
#196500
1$
b0 5
1+
#197000
0+
#197500
0$
b1 5
b1111 I
1+
#198000
0+
#198500
b10 5
1+
#199000
0+
#199500
b11 5
1+
#200000
0+
#200500
b100 5
1+
#201000
0+
#201500
b101 5
1+
#202000
0+
#202500
1$
b0 5
1+
#203000
0+
#203500
0$
b1 5
b1 H
b101010 J
b0 I
1+
#204000
0+
#204500
0!
b10 5
1+
#205000
0+
#205500
b11 5
1+
#206000
0+
#206500
b100 5
1+
#207000
0+
#207500
b101 5
1+
#208000
0+
#208500
1$
b0 5
1+
#209000
0+
#209500
0$
b1 5
b1 I
1+
#210000
0+
#210500
b10 5
1+
#211000
0+
#211500
b11 5
1+
#212000
0+
#212500
b100 5
1+
#213000
0+
#213500
b101 5
1+
#214000
0+
#214500
1$
b0 5
1+
#215000
0+
#215500
0$
b1 5
b10 I
1+
#216000
0+
#216500
b10 5
1+
#217000
0+
#217500
b11 5
1+
#218000
0+
#218500
b100 5
1+
#219000
0+
#219500
b101 5
1+
#220000
0+
#220500
1$
b0 5
1+
#221000
0+
#221500
0$
b1 5
b11 I
1+
#222000
0+
#222500
b10 5
1+
#223000
0+
#223500
b11 5
1+
#224000
0+
#224500
b100 5
1+
#225000
0+
#225500
b101 5
1+
#226000
0+
#226500
1$
b0 5
1+
#227000
0+
#227500
0$
b1 5
b100 I
1+
#228000
0+
#228500
b10 5
1+
#229000
0+
#229500
b11 5
1+
#230000
0+
#230500
b100 5
1+
#231000
0+
#231500
b101 5
1+
#232000
0+
#232500
1$
b0 5
1+
#233000
0+
#233500
0$
b1 5
b101 I
1+
#234000
0+
#234500
b10 5
1+
#235000
0+
#235500
b11 5
1+
#236000
0+
#236500
b100 5
1+
#237000
0+
#237500
b101 5
1+
#238000
0+
#238500
1$
b0 5
1+
#239000
0+
#239500
0$
b1 5
b110 I
1+
#240000
0+
#240500
b10 5
1+
#241000
0+
#241500
b11 5
1+
#242000
0+
#242500
b100 5
1+
#243000
0+
#243500
b101 5
1+
#244000
0+
#244500
1$
b0 5
1+
#245000
0+
#245500
0$
b1 5
b111 I
1+
#246000
0+
#246500
b10 5
1+
#247000
0+
#247500
b11 5
1+
#248000
0+
#248500
b100 5
1+
#249000
0+
#249500
b101 5
1+
#250000
0+
#250500
1$
b0 5
1+
#251000
0+
#251500
0$
b1 5
b1000 I
1+
#252000
0+
#252500
b10 5
1+
#253000
0+
#253500
b11 5
1+
#254000
0+
#254500
b100 5
1+
#255000
0+
#255500
b101 5
1+
#256000
0+
#256500
1$
b0 5
1+
#257000
0+
#257500
0$
b1 5
b1001 I
1+
#258000
0+
#258500
b10 5
1+
#259000
0+
#259500
b11 5
1+
#260000
0+
#260500
b100 5
1+
#261000
0+
#261500
b101 5
1+
#262000
0+
#262500
1$
b0 5
1+
#263000
0+
#263500
0$
b1 5
b1010 I
1+
#264000
0+
#264500
b10 5
1+
#265000
0+
#265500
b11 5
1+
#266000
0+
#266500
b100 5
1+
#267000
0+
#267500
b101 5
1+
#268000
0+
#268500
1$
b0 5
1+
#269000
0+
#269500
0$
b1 5
b1011 I
1+
#270000
0+
#270500
b10 5
1+
#271000
0+
#271500
b11 5
1+
#272000
0+
#272500
b100 5
1+
#273000
0+
#273500
b101 5
1+
#274000
0+
#274500
1$
b0 5
1+
#275000
0+
#275500
0$
b1 5
b1100 I
1+
#276000
0+
#276500
b10 5
1+
#277000
0+
#277500
b11 5
1+
#278000
0+
#278500
b100 5
1+
#279000
0+
#279500
b101 5
1+
#280000
0+
#280500
1$
b0 5
1+
#281000
0+
#281500
0$
b1 5
b1101 I
1+
#282000
0+
#282500
b10 5
1+
#283000
0+
#283500
b11 5
1+
#284000
0+
#284500
b100 5
1+
#285000
0+
#285500
b101 5
1+
#286000
0+
#286500
1$
b0 5
1+
#287000
0+
#287500
0$
b1 5
b1110 I
1+
#288000
0+
#288500
b10 5
1+
#289000
0+
#289500
b11 5
1+
#290000
0+
#290500
b100 5
1+
#291000
0+
#291500
b101 5
1+
#292000
0+
#292500
1$
b0 5
1+
#293000
0+
#293500
0$
b1 5
b1111 I
1+
#294000
0+
#294500
b10 5
1+
#295000
0+
#295500
b11 5
1+
#296000
0+
#296500
b100 5
1+
#297000
0+
#297500
b101 5
1+
#298000
0+
#298500
1$
b0 5
1+
#299000
0+
#299500
0$
b1 5
b10 H
b10101 J
b0 I
1+
#300000
0+
#300500
1!
b10 5
1+
#301000
0+
#301500
b11 5
1+
#302000
0+
#302500
b100 5
1+
#303000
0+
#303500
b101 5
1+
#304000
0+
#304500
1$
b0 5
1+
#305000
0+
#305500
0$
b1 5
b1 I
1+
#306000
0+
#306500
b10 5
1+
#307000
0+
#307500
b11 5
1+
#308000
0+
#308500
b100 5
1+
#309000
0+
#309500
b101 5
1+
#310000
0+
#310500
1$
b0 5
1+
#311000
0+
#311500
0$
b1 5
b10 I
1+
#312000
0+
#312500
b10 5
1+
#313000
0+
#313500
b11 5
1+
#314000
0+
#314500
b100 5
1+
#315000
0+
#315500
b101 5
1+
#316000
0+
#316500
1$
b0 5
1+
#317000
0+
#317500
0$
b1 5
b11 I
1+
#318000
0+
#318500
b10 5
1+
#319000
0+
#319500
b11 5
1+
#320000
0+
#320500
b100 5
1+
#321000
0+
#321500
b101 5
1+
#322000
0+
#322500
1$
b0 5
1+
#323000
0+
#323500
0$
b1 5
b100 I
1+
#324000
0+
#324500
b10 5
1+
#325000
0+
#325500
b11 5
1+
#326000
0+
#326500
b100 5
1+
#327000
0+
#327500
b101 5
1+
#328000
0+
#328500
1$
b0 5
1+
#329000
0+
#329500
0$
b1 5
b101 I
1+
#330000
0+
#330500
b10 5
1+
#331000
0+
#331500
b11 5
1+
#332000
0+
#332500
b100 5
1+
#333000
0+
#333500
b101 5
1+
#334000
0+
#334500
1$
b0 5
1+
#335000
0+
#335500
0$
b1 5
b110 I
1+
#336000
0+
#336500
b10 5
1+
#337000
0+
#337500
b11 5
1+
#338000
0+
#338500
b100 5
1+
#339000
0+
#339500
b101 5
1+
#340000
0+
#340500
1$
b0 5
1+
#341000
0+
#341500
0$
b1 5
b111 I
1+
#342000
0+
#342500
b10 5
1+
#343000
0+
#343500
b11 5
1+
#344000
0+
#344500
b100 5
1+
#345000
0+
#345500
b101 5
1+
#346000
0+
#346500
1$
b0 5
1+
#347000
0+
#347500
0$
b1 5
b1000 I
1+
#348000
0+
#348500
b10 5
1+
#349000
0+
#349500
b11 5
1+
#350000
0+
#350500
b100 5
1+
#351000
0+
#351500
b101 5
1+
#352000
0+
#352500
1$
b0 5
1+
#353000
0+
#353500
0$
b1 5
b1001 I
1+
#354000
0+
#354500
b10 5
1+
#355000
0+
#355500
b11 5
1+
#356000
0+
#356500
b100 5
1+
#357000
0+
#357500
b101 5
1+
#358000
0+
#358500
1$
b0 5
1+
#359000
0+
#359500
0$
b1 5
b1010 I
1+
#360000
0+
#360500
b10 5
1+
#361000
0+
#361500
b11 5
1+
#362000
0+
#362500
b100 5
1+
#363000
0+
#363500
b101 5
1+
#364000
0+
#364500
1$
b0 5
1+
#365000
0+
#365500
0$
b1 5
b1011 I
1+
#366000
0+
#366500
b10 5
1+
#367000
0+
#367500
b11 5
1+
#368000
0+
#368500
b100 5
1+
#369000
0+
#369500
b101 5
1+
#370000
0+
#370500
1$
b0 5
1+
#371000
0+
#371500
0$
b1 5
b1100 I
1+
